queueio/__init__.py
queueio-0.1.2.dist-info/DESCRIPTION.rst
queueio-0.1.2.dist-info/METADATA
queueio-0.1.2.dist-info/RECORD
queueio-0.1.2.dist-info/WHEEL
queueio-0.1.2.dist-info/metadata.json
queueio-0.1.2.dist-info/top_level.txt
